eDOCr/ocr_it.py
eDOCr/keras_ocr/__init__.py
eDOCr/keras_ocr/config.py
eDOCr/keras_ocr/data_generation.py
eDOCr/keras_ocr/datasets.py
eDOCr/keras_ocr/detection.py
eDOCr/keras_ocr/evaluation.py
eDOCr/keras_ocr/pipeline.py
eDOCr/keras_ocr/recognition.py
eDOCr/keras_ocr/tools.py
eDOCr/keras_ocr_models/__init__.py
eDOCr/keras_ocr_models/train_recognizer.py
eDOCr/tools/__init__.py
eDOCr/tools/box_tree.py
eDOCr/tools/cluster.py
eDOCr/tools/img_process.py
eDOCr/tools/output.py
eDOCr/tools/pipeline_dimensions.py
eDOCr/tools/pipeline_gdts.py
eDOCr/tools/pipeline_infoblock.py
eDOCr/tools/tolerances.py
eDOCr/tools/watermark.py
eDOCr-0.0.4.dist-info/LICENSE
eDOCr-0.0.4.dist-info/METADATA
eDOCr-0.0.4.dist-info/WHEEL
eDOCr-0.0.4.dist-info/top_level.txt
eDOCr-0.0.4.dist-info/RECORD
