Metadata-Version: 2.1
Name: eDOCr
Version: 0.0.4
Summary: OCR for Engineering Mechanical Drawings
Author: Javier Villena Toro
Project-URL: Homepage, https://github.com/javvi51/eDOCr
Project-URL: Bug Tracker, https://github.com/javvi51/eDOCr/issues
Classifier: Programming Language :: Python :: 3
Classifier: License :: OSI Approved :: MIT License
Classifier: Operating System :: OS Independent
Requires-Python: >=3.7
License-File: LICENSE
Requires-Dist: opencv-python
Requires-Dist: tensorflow (>=2.0.0)
Requires-Dist: Pillow
Requires-Dist: shapely
Requires-Dist: anytree
Requires-Dist: scikit-image
Requires-Dist: scikit-learn
Requires-Dist: tqdm
Requires-Dist: validators
Requires-Dist: essential-generators
Requires-Dist: imgaug
Requires-Dist: fonttools
Requires-Dist: editdistance
Requires-Dist: pyclipper
Requires-Dist: efficientnet (==1.0.0)
Requires-Dist: pytest
Requires-Dist: pdf2image
